{
  "data": [
    {
      "id": "bitcoin-cash",
      "rank": "14",
      "symbol": "BCH",
      "name": "Bitcoin Cash",
      "supply": "19740090.6250000000000000",
      "maxSupply": "21000000.0000000000000000",
      "marketCapUsd": "8597125638.8919882058522331",
      "volumeUsd24Hr": "156654882.3185743511597983",
      "priceUsd": "435.5160167301404274",
      "changePercent24Hr": "-2.3775772272150559",
      "vwap24Hr": "441.3227058333678245",
      "explorer": "https://blockchair.com/bitcoin-cash/blocks"
    }
  ]
}